shieldcommit/__init__.py
shieldcommit/__main__.py
shieldcommit/aks_detector.py
shieldcommit/azure_db_detector.py
shieldcommit/eks_detector.py
shieldcommit/gcp_db_detector.py
shieldcommit/gcp_detector.py
shieldcommit/installer.py
shieldcommit/intelligent_detector.py
shieldcommit/rds_detector.py
shieldcommit/scanner.py
shieldcommit/utils.py
shieldcommit-1.0.0.dist-info/METADATA
shieldcommit-1.0.0.dist-info/WHEEL
shieldcommit-1.0.0.dist-info/entry_points.txt
shieldcommit-1.0.0.dist-info/top_level.txt
shieldcommit-1.0.0.dist-info/RECORD
