Metadata-Version: 2.4
Name: shieldcommit
Version: 1.0.0
Summary: Lightweight pre-commit secret scanner CLI with EKS/RDS version warnings
Author: TechiKrish
License: MIT
Classifier: Programming Language :: Python :: 3
Classifier: License :: OSI Approved :: MIT License
Requires-Python: >=3.8
Requires-Dist: click>=8.0
